{
  "patch_id": "microchip-same70-atsame70q21b-bootstrap",
  "device": "atsame70q21b",
  "package": "lqfp144",
  "core": "cortex-m7f",
  "summary": "Board-target SAME70 Xplained Ultra device.",
  "adc_internal_channels": [
    {
      "peripheral": "AFEC0",
      "kind": "temperature_sensor",
      "channel_index": 11
    }
  ],
  "adc_resolution_options": [
    {
      "peripheral": "AFEC0",
      "bits": 10,
      "field_value": 0
    },
    {
      "peripheral": "AFEC0",
      "bits": 12,
      "field_value": 1
    },
    {
      "peripheral": "AFEC0",
      "bits": 13,
      "field_value": 2
    },
    {
      "peripheral": "AFEC0",
      "bits": 14,
      "field_value": 3
    },
    {
      "peripheral": "AFEC1",
      "bits": 10,
      "field_value": 0
    },
    {
      "peripheral": "AFEC1",
      "bits": 12,
      "field_value": 1
    },
    {
      "peripheral": "AFEC1",
      "bits": 13,
      "field_value": 2
    },
    {
      "peripheral": "AFEC1",
      "bits": 14,
      "field_value": 3
    }
  ],
  "adc_max_clock_hz": 40000000,
  "system_clock_profiles": [
    {
      "profile_id": "safe-internal-12mhz",
      "kind": "safe",
      "source_kind": "internal-oscillator",
      "sysclk_hz": 12000000,
      "hclk_hz": 12000000,
      "pclk_hz": 12000000,
      "source_hz": 12000000,
      "oscillator_startup_cycles": 255,
      "mck_prescaler": 1
    },
    {
      "profile_id": "default-safe-internal-12mhz",
      "kind": "default",
      "source_kind": "internal-oscillator",
      "sysclk_hz": 12000000,
      "hclk_hz": 12000000,
      "pclk_hz": 12000000,
      "source_hz": 12000000,
      "oscillator_startup_cycles": 255,
      "mck_prescaler": 1
    },
    {
      "profile_id": "crystal-12mhz",
      "kind": "direct",
      "source_kind": "external-oscillator",
      "sysclk_hz": 12000000,
      "hclk_hz": 12000000,
      "pclk_hz": 12000000,
      "source_hz": 12000000,
      "oscillator_startup_cycles": 255,
      "mck_prescaler": 1
    },
    {
      "profile_id": "plla-150mhz",
      "kind": "performance",
      "source_kind": "pll-external",
      "sysclk_hz": 150000000,
      "hclk_hz": 150000000,
      "pclk_hz": 150000000,
      "source_hz": 12000000,
      "oscillator_startup_cycles": 255,
      "mck_prescaler": 2,
      "pll_m": 1,
      "pll_n": 24,
      "flash_latency": 6
    }
  ],
  "uart_baud_clock_sources": [
    {
      "peripheral": "USART0",
      "source": "mck",
      "field_value": 0
    },
    {
      "peripheral": "USART1",
      "source": "mck",
      "field_value": 0
    },
    {
      "peripheral": "USART2",
      "source": "mck",
      "field_value": 0
    },
    {
      "peripheral": "UART0",
      "source": "mck",
      "field_value": 0
    },
    {
      "peripheral": "UART1",
      "source": "mck",
      "field_value": 0
    },
    {
      "peripheral": "UART2",
      "source": "mck",
      "field_value": 0
    },
    {
      "peripheral": "UART3",
      "source": "mck",
      "field_value": 0
    },
    {
      "peripheral": "UART4",
      "source": "mck",
      "field_value": 0
    }
  ],
  "uart_baud_oversampling_options": [
    {
      "peripheral": "USART0",
      "ratio": 16,
      "field_value": 0
    },
    {
      "peripheral": "USART0",
      "ratio": 8,
      "field_value": 1
    },
    {
      "peripheral": "USART1",
      "ratio": 16,
      "field_value": 0
    },
    {
      "peripheral": "USART1",
      "ratio": 8,
      "field_value": 1
    },
    {
      "peripheral": "USART2",
      "ratio": 16,
      "field_value": 0
    },
    {
      "peripheral": "USART2",
      "ratio": 8,
      "field_value": 1
    },
    {
      "peripheral": "UART0",
      "ratio": 16,
      "field_value": 0
    },
    {
      "peripheral": "UART1",
      "ratio": 16,
      "field_value": 0
    },
    {
      "peripheral": "UART2",
      "ratio": 16,
      "field_value": 0
    },
    {
      "peripheral": "UART3",
      "ratio": 16,
      "field_value": 0
    },
    {
      "peripheral": "UART4",
      "ratio": 16,
      "field_value": 0
    }
  ],
  "uart_data_bits_options": [
    {
      "peripheral": "USART0",
      "bits": 5,
      "m0_value": 0,
      "m1_value": 0
    },
    {
      "peripheral": "USART0",
      "bits": 6,
      "m0_value": 1,
      "m1_value": 0
    },
    {
      "peripheral": "USART0",
      "bits": 7,
      "m0_value": 2,
      "m1_value": 0
    },
    {
      "peripheral": "USART0",
      "bits": 8,
      "m0_value": 3,
      "m1_value": 0
    },
    {
      "peripheral": "USART0",
      "bits": 9,
      "m0_value": 0,
      "m1_value": 1
    },
    {
      "peripheral": "USART1",
      "bits": 5,
      "m0_value": 0,
      "m1_value": 0
    },
    {
      "peripheral": "USART1",
      "bits": 6,
      "m0_value": 1,
      "m1_value": 0
    },
    {
      "peripheral": "USART1",
      "bits": 7,
      "m0_value": 2,
      "m1_value": 0
    },
    {
      "peripheral": "USART1",
      "bits": 8,
      "m0_value": 3,
      "m1_value": 0
    },
    {
      "peripheral": "USART1",
      "bits": 9,
      "m0_value": 0,
      "m1_value": 1
    },
    {
      "peripheral": "USART2",
      "bits": 5,
      "m0_value": 0,
      "m1_value": 0
    },
    {
      "peripheral": "USART2",
      "bits": 6,
      "m0_value": 1,
      "m1_value": 0
    },
    {
      "peripheral": "USART2",
      "bits": 7,
      "m0_value": 2,
      "m1_value": 0
    },
    {
      "peripheral": "USART2",
      "bits": 8,
      "m0_value": 3,
      "m1_value": 0
    },
    {
      "peripheral": "USART2",
      "bits": 9,
      "m0_value": 0,
      "m1_value": 1
    },
    {
      "peripheral": "UART0",
      "bits": 8,
      "m0_value": 0,
      "m1_value": 0
    },
    {
      "peripheral": "UART1",
      "bits": 8,
      "m0_value": 0,
      "m1_value": 0
    },
    {
      "peripheral": "UART2",
      "bits": 8,
      "m0_value": 0,
      "m1_value": 0
    },
    {
      "peripheral": "UART3",
      "bits": 8,
      "m0_value": 0,
      "m1_value": 0
    },
    {
      "peripheral": "UART4",
      "bits": 8,
      "m0_value": 0,
      "m1_value": 0
    }
  ],
  "uart_parity_options": [
    {
      "peripheral": "USART0",
      "parity": "even",
      "pce_value": 0,
      "ps_value": 0
    },
    {
      "peripheral": "USART0",
      "parity": "odd",
      "pce_value": 1,
      "ps_value": 0
    },
    {
      "peripheral": "USART0",
      "parity": "none",
      "pce_value": 4,
      "ps_value": 0
    },
    {
      "peripheral": "USART1",
      "parity": "even",
      "pce_value": 0,
      "ps_value": 0
    },
    {
      "peripheral": "USART1",
      "parity": "odd",
      "pce_value": 1,
      "ps_value": 0
    },
    {
      "peripheral": "USART1",
      "parity": "none",
      "pce_value": 4,
      "ps_value": 0
    },
    {
      "peripheral": "USART2",
      "parity": "even",
      "pce_value": 0,
      "ps_value": 0
    },
    {
      "peripheral": "USART2",
      "parity": "odd",
      "pce_value": 1,
      "ps_value": 0
    },
    {
      "peripheral": "USART2",
      "parity": "none",
      "pce_value": 4,
      "ps_value": 0
    },
    {
      "peripheral": "UART0",
      "parity": "even",
      "pce_value": 0,
      "ps_value": 0
    },
    {
      "peripheral": "UART0",
      "parity": "odd",
      "pce_value": 1,
      "ps_value": 0
    },
    {
      "peripheral": "UART0",
      "parity": "none",
      "pce_value": 4,
      "ps_value": 0
    },
    {
      "peripheral": "UART1",
      "parity": "even",
      "pce_value": 0,
      "ps_value": 0
    },
    {
      "peripheral": "UART1",
      "parity": "odd",
      "pce_value": 1,
      "ps_value": 0
    },
    {
      "peripheral": "UART1",
      "parity": "none",
      "pce_value": 4,
      "ps_value": 0
    },
    {
      "peripheral": "UART2",
      "parity": "even",
      "pce_value": 0,
      "ps_value": 0
    },
    {
      "peripheral": "UART2",
      "parity": "odd",
      "pce_value": 1,
      "ps_value": 0
    },
    {
      "peripheral": "UART2",
      "parity": "none",
      "pce_value": 4,
      "ps_value": 0
    },
    {
      "peripheral": "UART3",
      "parity": "even",
      "pce_value": 0,
      "ps_value": 0
    },
    {
      "peripheral": "UART3",
      "parity": "odd",
      "pce_value": 1,
      "ps_value": 0
    },
    {
      "peripheral": "UART3",
      "parity": "none",
      "pce_value": 4,
      "ps_value": 0
    },
    {
      "peripheral": "UART4",
      "parity": "even",
      "pce_value": 0,
      "ps_value": 0
    },
    {
      "peripheral": "UART4",
      "parity": "odd",
      "pce_value": 1,
      "ps_value": 0
    },
    {
      "peripheral": "UART4",
      "parity": "none",
      "pce_value": 4,
      "ps_value": 0
    }
  ],
  "uart_stop_bits_options": [
    {
      "peripheral": "USART0",
      "stop_bits_q8": 256,
      "field_value": 0
    },
    {
      "peripheral": "USART0",
      "stop_bits_q8": 384,
      "field_value": 1
    },
    {
      "peripheral": "USART0",
      "stop_bits_q8": 512,
      "field_value": 2
    },
    {
      "peripheral": "USART1",
      "stop_bits_q8": 256,
      "field_value": 0
    },
    {
      "peripheral": "USART1",
      "stop_bits_q8": 384,
      "field_value": 1
    },
    {
      "peripheral": "USART1",
      "stop_bits_q8": 512,
      "field_value": 2
    },
    {
      "peripheral": "USART2",
      "stop_bits_q8": 256,
      "field_value": 0
    },
    {
      "peripheral": "USART2",
      "stop_bits_q8": 384,
      "field_value": 1
    },
    {
      "peripheral": "USART2",
      "stop_bits_q8": 512,
      "field_value": 2
    },
    {
      "peripheral": "UART0",
      "stop_bits_q8": 256,
      "field_value": 0
    },
    {
      "peripheral": "UART1",
      "stop_bits_q8": 256,
      "field_value": 0
    },
    {
      "peripheral": "UART2",
      "stop_bits_q8": 256,
      "field_value": 0
    },
    {
      "peripheral": "UART3",
      "stop_bits_q8": 256,
      "field_value": 0
    },
    {
      "peripheral": "UART4",
      "stop_bits_q8": 256,
      "field_value": 0
    }
  ],
  "uart_mode_flags": [
    {
      "peripheral": "USART0",
      "supports_lin": true,
      "supports_irda": true,
      "supports_smartcard": true,
      "supports_half_duplex": true,
      "supports_synchronous": true,
      "supports_auto_baud": false,
      "supports_wake_from_stop": true
    },
    {
      "peripheral": "USART1",
      "supports_lin": true,
      "supports_irda": true,
      "supports_smartcard": true,
      "supports_half_duplex": true,
      "supports_synchronous": true,
      "supports_auto_baud": false,
      "supports_wake_from_stop": true
    },
    {
      "peripheral": "USART2",
      "supports_lin": true,
      "supports_irda": true,
      "supports_smartcard": true,
      "supports_half_duplex": true,
      "supports_synchronous": true,
      "supports_auto_baud": false,
      "supports_wake_from_stop": true
    },
    {
      "peripheral": "UART0",
      "supports_lin": false,
      "supports_irda": false,
      "supports_smartcard": false,
      "supports_half_duplex": false,
      "supports_synchronous": false,
      "supports_auto_baud": false,
      "supports_wake_from_stop": false
    },
    {
      "peripheral": "UART1",
      "supports_lin": false,
      "supports_irda": false,
      "supports_smartcard": false,
      "supports_half_duplex": false,
      "supports_synchronous": false,
      "supports_auto_baud": false,
      "supports_wake_from_stop": false
    },
    {
      "peripheral": "UART2",
      "supports_lin": false,
      "supports_irda": false,
      "supports_smartcard": false,
      "supports_half_duplex": false,
      "supports_synchronous": false,
      "supports_auto_baud": false,
      "supports_wake_from_stop": false
    },
    {
      "peripheral": "UART3",
      "supports_lin": false,
      "supports_irda": false,
      "supports_smartcard": false,
      "supports_half_duplex": false,
      "supports_synchronous": false,
      "supports_auto_baud": false,
      "supports_wake_from_stop": false
    },
    {
      "peripheral": "UART4",
      "supports_lin": false,
      "supports_irda": false,
      "supports_smartcard": false,
      "supports_half_duplex": false,
      "supports_synchronous": false,
      "supports_auto_baud": false,
      "supports_wake_from_stop": false
    }
  ],
  "uart_max_baud_hz": 8000000,
  "spi_baud_prescaler_options": [
    {
      "peripheral": "SPI0",
      "divisor": 1,
      "field_value": 1
    },
    {
      "peripheral": "SPI0",
      "divisor": 2,
      "field_value": 2
    },
    {
      "peripheral": "SPI0",
      "divisor": 4,
      "field_value": 4
    },
    {
      "peripheral": "SPI0",
      "divisor": 8,
      "field_value": 8
    },
    {
      "peripheral": "SPI0",
      "divisor": 16,
      "field_value": 16
    },
    {
      "peripheral": "SPI0",
      "divisor": 32,
      "field_value": 32
    },
    {
      "peripheral": "SPI0",
      "divisor": 64,
      "field_value": 64
    },
    {
      "peripheral": "SPI0",
      "divisor": 128,
      "field_value": 128
    },
    {
      "peripheral": "SPI1",
      "divisor": 1,
      "field_value": 1
    },
    {
      "peripheral": "SPI1",
      "divisor": 2,
      "field_value": 2
    },
    {
      "peripheral": "SPI1",
      "divisor": 4,
      "field_value": 4
    },
    {
      "peripheral": "SPI1",
      "divisor": 8,
      "field_value": 8
    },
    {
      "peripheral": "SPI1",
      "divisor": 16,
      "field_value": 16
    },
    {
      "peripheral": "SPI1",
      "divisor": 32,
      "field_value": 32
    },
    {
      "peripheral": "SPI1",
      "divisor": 64,
      "field_value": 64
    },
    {
      "peripheral": "SPI1",
      "divisor": 128,
      "field_value": 128
    }
  ],
  "spi_frame_size_options": [
    {
      "peripheral": "SPI0",
      "bits": 8,
      "field_value": 0
    },
    {
      "peripheral": "SPI0",
      "bits": 9,
      "field_value": 1
    },
    {
      "peripheral": "SPI0",
      "bits": 10,
      "field_value": 2
    },
    {
      "peripheral": "SPI0",
      "bits": 11,
      "field_value": 3
    },
    {
      "peripheral": "SPI0",
      "bits": 12,
      "field_value": 4
    },
    {
      "peripheral": "SPI0",
      "bits": 13,
      "field_value": 5
    },
    {
      "peripheral": "SPI0",
      "bits": 14,
      "field_value": 6
    },
    {
      "peripheral": "SPI0",
      "bits": 15,
      "field_value": 7
    },
    {
      "peripheral": "SPI0",
      "bits": 16,
      "field_value": 8
    },
    {
      "peripheral": "SPI1",
      "bits": 8,
      "field_value": 0
    },
    {
      "peripheral": "SPI1",
      "bits": 9,
      "field_value": 1
    },
    {
      "peripheral": "SPI1",
      "bits": 10,
      "field_value": 2
    },
    {
      "peripheral": "SPI1",
      "bits": 11,
      "field_value": 3
    },
    {
      "peripheral": "SPI1",
      "bits": 12,
      "field_value": 4
    },
    {
      "peripheral": "SPI1",
      "bits": 13,
      "field_value": 5
    },
    {
      "peripheral": "SPI1",
      "bits": 14,
      "field_value": 6
    },
    {
      "peripheral": "SPI1",
      "bits": 15,
      "field_value": 7
    },
    {
      "peripheral": "SPI1",
      "bits": 16,
      "field_value": 8
    }
  ],
  "spi_mode_flags": [
    {
      "peripheral": "SPI0",
      "supports_crc": false,
      "supports_ti_frame": false,
      "supports_motorola_frame": true,
      "supports_i2s_submode": false,
      "supports_bidirectional_3wire": false,
      "supports_lsb_first": false,
      "supports_nss_hw_management": true
    },
    {
      "peripheral": "SPI1",
      "supports_crc": false,
      "supports_ti_frame": false,
      "supports_motorola_frame": true,
      "supports_i2s_submode": false,
      "supports_bidirectional_3wire": false,
      "supports_lsb_first": false,
      "supports_nss_hw_management": true
    }
  ],
  "peripheral_max_clock_hz": [
    {
      "peripheral": "USART0",
      "max_clock_hz": 150000000
    },
    {
      "peripheral": "USART1",
      "max_clock_hz": 150000000
    },
    {
      "peripheral": "USART2",
      "max_clock_hz": 150000000
    },
    {
      "peripheral": "UART0",
      "max_clock_hz": 150000000
    },
    {
      "peripheral": "UART1",
      "max_clock_hz": 150000000
    },
    {
      "peripheral": "UART2",
      "max_clock_hz": 150000000
    },
    {
      "peripheral": "UART3",
      "max_clock_hz": 150000000
    },
    {
      "peripheral": "UART4",
      "max_clock_hz": 150000000
    },
    {
      "peripheral": "SPI0",
      "max_clock_hz": 150000000
    },
    {
      "peripheral": "SPI1",
      "max_clock_hz": 150000000
    }
  ]
}
